pyved/__init__.py
pyved/__main__.py
pyved/_ecs_pattern.py
pyved/editor.py
pyved/menu_bar_ev_handler.py
pyved/menu_bar_gui.py
pyved/test.py
pyved/utils.py
pyved/data/VERSION
pyved/gui-rel-data/dropper_button.png
pyved/gui-rel-data/fill_button.png
pyved/gui-rel-data/paint_button.png
pyved/gui-rel-data/paint_icon.png
pyved/gui-rel-data/ui_theme.json
pyved/pong/ball.py
pyved/pong/bat.py
pyved/pong/pong.py
pyved/pong/score.py
pyved/pong/wall.py
pyved-0.1.1.dist-info/LICENSE
pyved-0.1.1.dist-info/METADATA
pyved-0.1.1.dist-info/WHEEL
pyved-0.1.1.dist-info/entry_points.txt
pyved-0.1.1.dist-info/top_level.txt
pyved-0.1.1.dist-info/RECORD
