Metadata-Version: 2.1
Name: pyved
Version: 0.1.1
Summary: experimental toolbox for game devs who use python
Home-page: https://github.com/wkta/gamedev-pyved
Author: moonb3ndr et al.
Author-email: contact@kata.games
License: LGPL-3.0
License-File: LICENSE
Requires-Dist: pygame-ce (>=2.2.1)
Requires-Dist: pygame-gui (>=0.6.9)
Requires-Dist: requests (>=2.27.0)
Requires-Dist: pyved-engine (>=23.6a1)
